{
  "Name": "ax",
  "Description": "Deletes the provided ax record",
  "HttpMethod": "DELETE",
  "IsEnabled": true,
  "OrderIndex": 10,
  "CrossDomainPolicy": "PortalAliasesOnly",
  "Input": [
    {
      "Name": "RecordId",
      "IsDeleted": false,
      "IsEnabled": true,
      "OrderIndex": 0,
      "Parameters": {},
      "InputTypeStr": "text",
      "Validations": [
        {
          "Data": "{\"Message\":\"RecordId is required.\"}",
          "Type": "default-required",
          "IsDeleted": false,
          "IsEnabled": false,
          "OrderIndex": 0,
          "Metadata": {
            "PAP_InternalIdentifier": "Api.InputField.RequiredValidator"
          }
        }
      ]
    }
  ],
  "Actions": [
    {
      "ActionType": "PlantAnApp.DeleteEntity.b934ce90-ff1a-4999-a137-8fe7c9fa8e8e",
      "OrderIndex": 0,
      "Parameters": {
        "RecordId": "[RecordId]"
      },
      "IsEnabled": true,
      "ExecutionType": "OnExecute",
      "Metadata": {
        "PAP_InternalIdentifier": "Api.DeleteEntity",
        "EntityIdentifier": "b934ce90-ff1a-4999-a137-8fe7c9fa8e8e",
        "IsUidEnabled": "True"
      }
    },
    {
      "ActionType": "JsonObject",
      "OrderIndex": 1,
      "Parameters": {
        "HttpCode": "200 OK",
        "Fields": [],
        "Headers": []
      },
      "IsEnabled": true,
      "ExecutionType": "OnExecute",
      "Metadata": {
        "PAP_InternalIdentifier": "Api.Response"
      }
    }
  ],
  "OnErrorActions": []
}